aoiktopdownparser/__init__.py
aoiktopdownparser/__main__.py
aoiktopdownparser/demo/__init__.py
aoiktopdownparser/demo/calculator/__init__.py
aoiktopdownparser/demo/calculator/parser_rules.txt
aoiktopdownparser/demo/json/__init__.py
aoiktopdownparser/demo/json/parser_rules.txt
aoiktopdownparser/gen/__init__.py
aoiktopdownparser/gen/ast.py
aoiktopdownparser/gen/backtracking_funcs.py
aoiktopdownparser/gen/generator.py
aoiktopdownparser/gen/opts.py
aoiktopdownparser/gen/opts_const.py
aoiktopdownparser/gen/parser.py
aoiktopdownparser/gen/parser_rules.txt
aoiktopdownparser/gen/parser_tplt.py
aoiktopdownparser/gen/parser_tplt_example.py
aoiktopdownparser/main/__init__.py
aoiktopdownparser/main/argpsr.py
aoiktopdownparser/main/argpsr_const.py
aoiktopdownparser/main/main_const.py
aoiktopdownparser/main/main_imp.py
aoiktopdownparser/util/__init__.py
aoiktopdownparser/util/exc_util.py
aoiktopdownparser/util/indent_util.py
aoiktopdownparser/util/path_util.py
aoiktopdownparser/util/str_util.py
aoiktopdownparserdep/__init__.py
aoiktopdownparserdep/aoikargutil.py
aoiktopdownparserdep/aoikimportutil.py
AoikTopDownParser-0.4.1.dist-info/LICENSE.txt
AoikTopDownParser-0.4.1.dist-info/METADATA
AoikTopDownParser-0.4.1.dist-info/WHEEL
AoikTopDownParser-0.4.1.dist-info/entry_points.txt
AoikTopDownParser-0.4.1.dist-info/top_level.txt
AoikTopDownParser-0.4.1.dist-info/RECORD
