Metadata-Version: 2.1
Name: AoikTopDownParser
Version: 0.4.1
Summary: A top-down recursive descent predictive or backtracking parser generator.
Home-page: https://github.com/AoiKuiyuyou/AoikTopDownParser
Author: Aoi.Kuiyuyou
Author-email: aoi.kuiyuyou@gmail.com
License: MIT
Keywords: top down recursive descent predictive backtracking parser generator
Platform: UNKNOWN
Classifier: Development Status :: 5 - Production/Stable
Classifier: Environment :: Console
Classifier: Intended Audience :: Developers
Classifier: License :: OSI Approved :: MIT License
Classifier: Operating System :: OS Independent 
Classifier: Programming Language :: Python :: 2
Classifier: Programming Language :: Python :: 2.7
Classifier: Programming Language :: Python :: 3
